django_subdomains_chiniki-2.1.0.dist-info/DESCRIPTION.rst
django_subdomains_chiniki-2.1.0.dist-info/METADATA
django_subdomains_chiniki-2.1.0.dist-info/RECORD
django_subdomains_chiniki-2.1.0.dist-info/WHEEL
django_subdomains_chiniki-2.1.0.dist-info/metadata.json
django_subdomains_chiniki-2.1.0.dist-info/top_level.txt
subdomains/__init__.py
subdomains/middleware.py
subdomains/models.py
subdomains/utils.py
subdomains/templatetags/__init__.py
subdomains/templatetags/subdomainurls.py
subdomains/tests/__init__.py
subdomains/tests/tests.py
subdomains/tests/views.py
subdomains/tests/urls/__init__.py
subdomains/tests/urls/api.py
subdomains/tests/urls/application.py
subdomains/tests/urls/default.py
subdomains/tests/urls/marketing.py
