Metadata-Version: 2.0
Name: django-subdomains-chiniki
Version: 2.1.0
Summary: Subdomain tools for the Django framework, including subdomain-based URL routing.
Home-page: https://github.com/babdulhakim2/django-subdomains-chnk.git
Author: Abdulhakim Bashir
Author-email: babdulhakim2@gmail.com
License: MIT License
Platform: UNKNOWN
Requires-Dist: django
